fermilite_ariba.cpython-37m-darwin.so
minimap_ariba.cpython-37m-darwin.so
vcfcall_ariba.cpython-37m-darwin.so
ariba/__init__.py
ariba/aln_to_metadata.py
ariba/assembly.py
ariba/assembly_compare.py
ariba/assembly_variants.py
ariba/bam_parse.py
ariba/card_record.py
ariba/cdhit.py
ariba/cluster.py
ariba/clusters.py
ariba/common.py
ariba/external_progs.py
ariba/faidx.py
ariba/flag.py
ariba/histogram.py
ariba/link.py
ariba/mapping.py
ariba/megares_data_finder.py
ariba/megares_zip_parser.py
ariba/mic_plotter.py
ariba/mlst_profile.py
ariba/mlst_reporter.py
ariba/pubmlst_getter.py
ariba/pubmlst_ref_preparer.py
ariba/read_filter.py
ariba/read_store.py
ariba/ref_genes_getter.py
ariba/ref_preparer.py
ariba/ref_seq_chooser.py
ariba/refdata_query.py
ariba/reference_data.py
ariba/report.py
ariba/report_filter.py
ariba/report_flag_expander.py
ariba/samtools_variants.py
ariba/scaffold_graph.py
ariba/sequence_metadata.py
ariba/sequence_variant.py
ariba/summary.py
ariba/summary_cluster.py
ariba/summary_cluster_variant.py
ariba/summary_sample.py
ariba/tb.py
ariba/versions.py
ariba/vfdb_parser.py
ariba/tasks/__init__.py
ariba/tasks/aln2meta.py
ariba/tasks/expandflag.py
ariba/tasks/flag.py
ariba/tasks/getref.py
ariba/tasks/micplot.py
ariba/tasks/prepareref.py
ariba/tasks/prepareref_tb.py
ariba/tasks/pubmlstget.py
ariba/tasks/pubmlstspecies.py
ariba/tasks/refquery.py
ariba/tasks/reportfilter.py
ariba/tasks/run.py
ariba/tasks/summary.py
ariba/tasks/test.py
ariba/tasks/version.py
ariba/tb_data/NC_000962.3.fa.gz
ariba/tb_data/NC_000962.3.gb
ariba/tb_data/panel.20181115.json
ariba/tb_data/panel.20181115.txt
ariba/tb_data/panel.20181221.json
ariba/tb_data/panel.20181221.txt
ariba/tb_data/panel.20190102.json
ariba/tb_data/panel.20190102.txt
ariba/test_run_data/metadata.tsv
ariba/test_run_data/reads_1.fq
ariba/test_run_data/reads_2.fq
ariba/test_run_data/ref_fasta_to_make_reads_from.fa
ariba/test_run_data/ref_seqs.fa
ariba/tests/__init__.py
ariba/tests/aln_to_metadata_test.py
ariba-2.14.6.dist-info/AUTHORS
ariba-2.14.6.dist-info/LICENSE
ariba-2.14.6.dist-info/METADATA
ariba-2.14.6.dist-info/WHEEL
ariba-2.14.6.dist-info/top_level.txt
ariba-2.14.6.dist-info/RECORD
